handsfree/__init__.cp38-win_amd64.pyd
handsfree/api/__init__.cp38-win_amd64.pyd
handsfree/api/activation.cp38-win_amd64.pyd
handsfree/api/app.cp38-win_amd64.pyd
handsfree/api/config.cp38-win_amd64.pyd
handsfree/api/index.cp38-win_amd64.pyd
handsfree/api/updater.cp38-win_amd64.pyd
handsfree/basic/__init__.cp38-win_amd64.pyd
handsfree/basic/constants.cp38-win_amd64.pyd
handsfree/basic/context.cp38-win_amd64.pyd
handsfree/basic/dicts.cp38-win_amd64.pyd
handsfree/basic/emitter.cp38-win_amd64.pyd
handsfree/basic/env.cp38-win_amd64.pyd
handsfree/basic/exception.cp38-win_amd64.pyd
handsfree/basic/http.cp38-win_amd64.pyd
handsfree/basic/logger.cp38-win_amd64.pyd
handsfree/basic/logging.cp38-win_amd64.pyd
handsfree/basic/machine_id.cp38-win_amd64.pyd
handsfree/basic/merge.cp38-win_amd64.pyd
handsfree/basic/package.cp38-win_amd64.pyd
handsfree/basic/thread_helper.cp38-win_amd64.pyd
handsfree/basic/utils.cp38-win_amd64.pyd
handsfree/build/anchor.cp38-win_amd64.pyd
handsfree/build/build.cp38-win_amd64.pyd
handsfree/build/NSIS/setup.nsi
handsfree/config/app.cp38-win_amd64.pyd
handsfree/handsfree.cp38-win_amd64.pyd
handsfree/webview/js_api.cp38-win_amd64.pyd
handsfree-0.1.3.dist-info/WHEEL
handsfree-0.1.3.dist-info/METADATA
handsfree-0.1.3.dist-info/RECORD
